LICENSE
MANIFEST.in
Makefile
README.rst
setup.cfg
setup.py
docs/Makefile
docs/cmd.rst
docs/conf.py
docs/index.rst
docs/intro.rst
docs/net.rst
docs/path.rst
docs/prompt.rst
docs/readme_head.rst
docs/utilities.rst
docs/_build/app.yaml
docs/_build/gae.py
docs/_build/html/.buildinfo
docs/_build/html/cmd.html
docs/_build/html/genindex.html
docs/_build/html/index.html
docs/_build/html/intro.html
docs/_build/html/net.html
docs/_build/html/objects.inv
docs/_build/html/path.html
docs/_build/html/prompt.html
docs/_build/html/py-modindex.html
docs/_build/html/readme_head.html
docs/_build/html/search.html
docs/_build/html/searchindex.js
docs/_build/html/utilities.html
docs/_build/html/_sources/cmd.txt
docs/_build/html/_sources/index.txt
docs/_build/html/_sources/intro.txt
docs/_build/html/_sources/net.txt
docs/_build/html/_sources/path.txt
docs/_build/html/_sources/prompt.txt
docs/_build/html/_sources/readme_head.txt
docs/_build/html/_sources/utilities.txt
docs/_build/html/_static/basic.css
docs/_build/html/_static/doctools.js
docs/_build/html/_static/file.png
docs/_build/html/_static/jquery.js
docs/_build/html/_static/minus.png
docs/_build/html/_static/nature.css
docs/_build/html/_static/plus.png
docs/_build/html/_static/pygments.css
docs/_build/html/_static/searchtools.js
docs/_build/html/_static/underscore.js
docs/_gae/app.yaml
docs/_gae/gae.py
docs/_python/prompt_session.py
docs/_static/.i
docs/_templates/layout.html
docs/_theme/nature/theme.conf
docs/_theme/nature/static/nature.css_t
docs/_theme/nature/static/pygments.css
sy/__init__.py
sy/_internal.py
sy/cmd.py
sy/exception.py
sy/log.py
sy/path.py
sy/prompt.py
sy/util.py
sy.egg-info/PKG-INFO
sy.egg-info/SOURCES.txt
sy.egg-info/dependency_links.txt
sy.egg-info/requires.txt
sy.egg-info/top_level.txt
sy/net/__init__.py
sy/net/ip.py
sy/net/remote.py
sy/net/intf/__init__.py
sy/net/intf/solaris10.py
tests/__init__.py
tests/__init__.pyc
tests/test_cmd.py
tests/test_cmd.pyc
tests/test_internal.py
tests/test_internal.pyc
tests/test_intf.py
tests/test_intf.pyc
tests/test_path.py
tests/test_path.pyc
tests/test_remote_download.py
