Metadata-Version: 1.0
Name: sy
Version: 0.3
Summary: Simple tools for system administration tasks
Home-page: http://sy.afajl.com
Author: Paul Diaconescu
Author-email: p@afajl.com
License: BSD
Platform: Python 2.4 and later on Unix
Classifier: Development Status :: 3 - Alpha
Classifier: Environment :: Console
Classifier: Intended Audience :: Developers
Classifier: License :: OSI Approved :: BSD License
Classifier: Operating System :: Unix
Classifier: Programming Language :: Python
Classifier: Topic :: System :: Systems Administration
Classifier: Topic :: Software Development :: Libraries :: Python Modules
